jupytexmagic/__init__.py
jupytexmagic/jupytexmagic.py
jupytexmagic/.ipynb_checkpoints/jupytexmagic-checkpoint.py
jupytexmagic-0.1.2.dist-info/LICENSE
jupytexmagic-0.1.2.dist-info/WHEEL
jupytexmagic-0.1.2.dist-info/METADATA
jupytexmagic-0.1.2.dist-info/RECORD
