Metadata-Version: 2.1
Name: jupytexmagic
Version: 0.1.2
Summary: This is the jupytexmagic module.
Author-email: Ross Mikulskis <rkulskis@gmail.com>
Classifier: License :: OSI Approved :: MIT License
Classifier: Framework :: IPython
Project-URL: Home, https://github.com/rkulskis/jupytex
